iotery_embedded_python_sdk/Iotery.py
iotery_embedded_python_sdk/README.md
iotery_embedded_python_sdk/__init__.py
iotery_embedded_python_sdk/api.json
iotery_embedded_python_sdk/example.py
iotery_embedded_python_sdk-0.1.14.data/data/api/api.json
iotery_embedded_python_sdk-0.1.14.dist-info/METADATA
iotery_embedded_python_sdk-0.1.14.dist-info/WHEEL
iotery_embedded_python_sdk-0.1.14.dist-info/top_level.txt
iotery_embedded_python_sdk-0.1.14.dist-info/RECORD
