Metadata-Version: 2.1
Name: iotery-embedded-python-sdk
Version: 0.1.14
Summary: iotery.io embedded python SDK
Home-page: https://github.com/bjyurkovich/iotery-embedded-python-sdk
Author: bjyurkovich
Author-email: bj.yurkovich@technicity.io
License: MIT
Platform: UNKNOWN
Classifier: Programming Language :: Python :: 3
Classifier: License :: OSI Approved :: MIT License
Classifier: Operating System :: OS Independent
Requires-Dist: requests
